pashto/__init__.py
pashto-0.0.1.dist-info/LICENSE
pashto-0.0.1.dist-info/METADATA
pashto-0.0.1.dist-info/WHEEL
pashto-0.0.1.dist-info/top_level.txt
pashto-0.0.1.dist-info/RECORD
