Metadata-Version: 2.1
Name: pashto
Version: 0.0.1
Summary: Pashto NLP Toolkit
Author-email: Ijazul Haq <ijazse@hotmail.com>
Project-URL: Homepage, https://github.com/ijazul-haq/pashto
Classifier: Programming Language :: Python :: 3
Classifier: License :: OSI Approved :: MIT License
Classifier: Operating System :: OS Independent
Requires-Python: >=3.7
License-File: LICENSE
